{"Bildung":"#FFC000",
"Bildung, Freizeit":"#BBAA1E",
"Dienstleistungen":"#538DD5",
"Erholung, Freizeit":"#638555",
"Erholung, Religion":"#094409",
"Freizeit, Kultur":"#B27A08",
"Freizeit, Sport":"#194761",
"Gesellschaft":"#B0CBEC",
"Gesellschaft, Kultur":"#E26B0A",
"Gesellschaft, öffentliche Dienstleistungen":"#569AD6",
"Gesundheit":"#CB0D0D",
"öffentliche Dienstleistungen":"#417DD4",
"Orientierung":"#BFBFBF",
"Sport":"#0141CF",
"Stadtbild":"#695656",
"Kinderbetreuung":"#00A0B0",
"öffentliche Dienstleistungen, Religion":"#476D93",
"Mobilität":"#6BB6D7",
"Religion":"#0D0D0D"}
